{
  "id": 1753896724069,
  "isim": "AAA_2",
  "not": "",
  "arsiv": false,
  "haftalar": [
    {
      "haftaNo": 1,
      "baslangic": "2025-07-28",
      "bitis": "2025-08-03",
      "aciklama": "",
      "pdf": null,
      "pdfName": "SELMA COŞKUN LOW CARB 1. hafta.pdf",
      "pdfOrijinalIsim": "SELMA COŞKUN LOW CARB 1. hafta.pdf",
      "pdfYolu": "pdfs/SELMA COŞKUN LOW CARB 1. hafta.pdf",
      "githubUrl": "https://github.com/mustafasacar35/lipodem-takip-paneli/blob/main/pdfs/SELMA COŞKUN LOW CARB 1. hafta.pdf",
      "indirmeUrl": "https://raw.githubusercontent.com/mustafasacar35/lipodem-takip-paneli/main/pdfs/SELMA COŞKUN LOW CARB 1. hafta.pdf",
      "kayitTarihi": "2025-07-30T17:32:43.971Z",
      "tarifKartlar": [],
      "tarifler": [],
      "gptMesaj": "",
      "pdfFile": {}
    }
  ],
  "sonGuncelleme": "2025-07-30T17:32:43.972Z",
  "githubKaydedildi": true
}